pylibpostal.libs/libpostal-858773f9.so.1.0.1
pylibpostal/pynormalize.c
pylibpostal/_tokenize.cpython-38-x86_64-linux-gnu.so
pylibpostal/_token_types.cpython-38-x86_64-linux-gnu.so
pylibpostal/expand.py
pylibpostal/pytokentypes.c
pylibpostal/__init__.py
pylibpostal/_expand.cpython-38-x86_64-linux-gnu.so
pylibpostal/pytokenize.c
pylibpostal/pyexpand.c
pylibpostal/_normalize.cpython-38-x86_64-linux-gnu.so
pylibpostal/pyutils.h
pylibpostal/dedupe.py
pylibpostal/parser.py
pylibpostal/pyparser.c
pylibpostal/pydedupe.c
pylibpostal/tokenize.py
pylibpostal/_near_dupe.cpython-38-x86_64-linux-gnu.so
pylibpostal/pyutils.c
pylibpostal/token_types.py
pylibpostal/near_dupe.py
pylibpostal/pyneardupe.c
pylibpostal/_dedupe.cpython-38-x86_64-linux-gnu.so
pylibpostal/_parser.cpython-38-x86_64-linux-gnu.so
pylibpostal/normalize.py
pylibpostal/utils/__init__.py
pylibpostal/utils/enum.py
pylibpostal/utils/encoding.py
pylibpostal-1.0.0.dist-info/LICENSE
pylibpostal-1.0.0.dist-info/METADATA
pylibpostal-1.0.0.dist-info/RECORD
pylibpostal-1.0.0.dist-info/WHEEL
